hwsis/__init__.py
hwsis/auth/__init__.py
hwsis/auth/aksk_service.py
hwsis/auth/signer.py
hwsis/auth/token_service.py
hwsis/bean/__init__.py
hwsis/bean/asr_request.py
hwsis/bean/callback.py
hwsis/bean/hot_word_request.py
hwsis/bean/pa_request.py
hwsis/bean/rasr_request.py
hwsis/bean/rtts_request.py
hwsis/bean/sis_config.py
hwsis/bean/tts_request.py
hwsis/client/__init__.py
hwsis/client/asr_client.py
hwsis/client/hot_word_client.py
hwsis/client/pa_client.py
hwsis/client/rasr_client.py
hwsis/client/rtts_client.py
hwsis/client/tts_client.py
hwsis/exception/__init__.py
hwsis/exception/exceptions.py
hwsis/utils/__init__.py
hwsis/utils/http_utils.py
hwsis/utils/io_utils.py
hwsis/utils/logger_utils.py
hwsis-0.0.4.dist-info/METADATA
hwsis-0.0.4.dist-info/WHEEL
hwsis-0.0.4.dist-info/top_level.txt
hwsis-0.0.4.dist-info/RECORD
