Metadata-Version: 2.1
Name: hwsis
Version: 0.0.4
Summary: SUCCESS
Home-page: https://www.google.com/google
Author: John John
Author-email: abcdefghigk@gmail.com
License: UNKNOWN
Platform: UNKNOWN
Classifier: Programming Language :: Python :: 3
Classifier: License :: OSI Approved :: MIT License
Classifier: Operating System :: OS Independent
